Metadata-Version: 1.0
Name: hearthstonecarddetector
Version: 0.1.4
Summary: match a specific cropped image to a hearthstone card id
Home-page: https://www.github.com/russon77/hearthstonecarddetector
Author: Tristan Kernan
Author-email: russon77@gmail.com
License: MIT
Keywords: hearthstone
Platform: UNKNOWN
